macro_expander/__init__.py
macro_expander/our_macros.py
macro_expander/scripts/__init__.py
macro_expander/scripts/expand_macros.py
macro_expander-0.4.0.dist-info/METADATA
macro_expander-0.4.0.dist-info/WHEEL
macro_expander-0.4.0.dist-info/entry_points.txt
macro_expander-0.4.0.dist-info/RECORD
