Metadata-Version: 2.3
Name: macro-expander
Version: 0.4.0
Summary: Expand macros within a text string. Somewhere between formatting and templating.
Requires-Python: >=3.5
Requires-Dist: pyparsing>=3.1.4
